tap_instantly_ai/__init__.py
tap_instantly_ai/__main__.py
tap_instantly_ai/client.py
tap_instantly_ai/schemas/__init__.py
tap_instantly_ai/schemas/analytics_campaign_count.json
tap_instantly_ai/schemas/analytics_campaign_summary.json
tap_instantly_ai/schemas/campaign_status.json
tap_instantly_ai/schemas/campaigns.json
tap_instantly_ai/streams.py
tap_instantly_ai/tap.py
tap_instantly_ai-0.0.1.dist-info/LICENSE
tap_instantly_ai-0.0.1.dist-info/METADATA
tap_instantly_ai-0.0.1.dist-info/WHEEL
tap_instantly_ai-0.0.1.dist-info/entry_points.txt
tap_instantly_ai-0.0.1.dist-info/RECORD
