Metadata-Version: 2.1
Name: tap-instantly-ai
Version: 0.0.1
Summary: `tap-instantly-ai` is a Singer tap for InstantlyAI, built with the Meltano Singer SDK.
License: Apache-2.0
Keywords: ELT,InstantlyAI
Author: Barbora Drinkova
Author-email: barbora.drinkova@strv.com
Requires-Python: >=3.8
Classifier: Intended Audience :: Developers
Classifier: License :: OSI Approved :: Apache Software License
Classifier: Operating System :: OS Independent
Classifier: Programming Language :: Python :: 3
Classifier: Programming Language :: Python :: 3.8
Classifier: Programming Language :: Python :: 3.9
Classifier: Programming Language :: Python :: 3.10
Classifier: Programming Language :: Python :: 3.11
Classifier: Programming Language :: Python :: 3.12
Provides-Extra: s3
Requires-Dist: fs-s3fs (>=1.1.1,<1.2.0) ; extra == "s3"
Requires-Dist: importlib-resources (==6.1.*) ; python_version < "3.9"
Requires-Dist: requests (>=2.31.0,<2.32.0)
Requires-Dist: singer-sdk (>=0.35.1,<0.36.0)
